odoo/addons/mgmtsystem_partner/README.rst
odoo/addons/mgmtsystem_partner/__init__.py
odoo/addons/mgmtsystem_partner/__manifest__.py
odoo/addons/mgmtsystem_partner/i18n/es.po
odoo/addons/mgmtsystem_partner/i18n/it.po
odoo/addons/mgmtsystem_partner/i18n/mgmtsystem_partner.pot
odoo/addons/mgmtsystem_partner/models/__init__.py
odoo/addons/mgmtsystem_partner/models/res_partner.py
odoo/addons/mgmtsystem_partner/readme/CONTRIBUTORS.rst
odoo/addons/mgmtsystem_partner/readme/DESCRIPTION.rst
odoo/addons/mgmtsystem_partner/readme/HISTORY.rst
odoo/addons/mgmtsystem_partner/readme/USAGE.rst
odoo/addons/mgmtsystem_partner/static/description/icon.png
odoo/addons/mgmtsystem_partner/static/description/index.html
odoo14_addon_mgmtsystem_partner-14.0.1.0.1.dev8.dist-info/METADATA
odoo14_addon_mgmtsystem_partner-14.0.1.0.1.dev8.dist-info/WHEEL
odoo14_addon_mgmtsystem_partner-14.0.1.0.1.dev8.dist-info/top_level.txt
odoo14_addon_mgmtsystem_partner-14.0.1.0.1.dev8.dist-info/RECORD
