Metadata-Version: 2.1
Name: odoo14-addon-mgmtsystem-partner
Version: 14.0.1.0.1.dev8
Summary: Add Management System reference on Partner's Contacts.
Home-page: https://github.com/OCA/management-system
Author: Associazione PNLUG - Gruppo Odoo, Odoo Community Association (OCA)
Author-email: support@odoo-community.org
License: AGPL-3
Platform: UNKNOWN
Classifier: Programming Language :: Python
Classifier: Framework :: Odoo
Classifier: Framework :: Odoo :: 14.0
Classifier: License :: OSI Approved :: GNU Affero General Public License v3
Classifier: Development Status :: 4 - Beta
Requires-Python: >=3.6
Requires-Dist: odoo <14.1dev,>=14.0a
